pangaea
tests
