Metadata-Version: 1.1
Name: pangaea
Version: 0.0.3
Summary: An xarray extension for land surface models.
Home-page: https://github.com/snowman2/pangaea
Author: Alan D. Snow
Author-email: alansnow21@gmail.com
License: BSD 3-Clause
Keywords: land surface model,xarray,gdal
Platform: UNKNOWN
Classifier: Intended Audience :: Developers
Classifier: Intended Audience :: Science/Research
Classifier: Operating System :: OS Independent
Classifier: Programming Language :: Python
Classifier: Programming Language :: Python :: 2
Classifier: Programming Language :: Python :: 2.7
Classifier: Programming Language :: Python :: 3
Classifier: Programming Language :: Python :: 3.5
Classifier: Programming Language :: Python :: 3.6
